{
"type": "FeatureCollection",
"name": "estrellaverde",
"crs": { "type": "name", "properties": { "name": "urn:ogc:def:crs:OGC:1.3:CRS84" } },
"features": [
{ "type": "Feature", "properties": { "fid": 4, "Name": "MIC5", "Nombre": "Ricard Camarena", "Dirección": "Avenida Burjassot 54", "Municipio": "València", "Web": "https://www.ricardcamarenarestaurant.com/", "Distinción": "2* MICHELIN y ESTRELLA VERDE MICHELIN" }, "geometry": { "type": "Point", "coordinates": [ -0.38525261286158, 39.4852533195399, 0.0 ] } },
{ "type": "Feature", "properties": { "fid": 15, "Name": "MIC20", "Nombre": "Cal Paradís", "Dirección": "Avenida Vilafranca 30", "Municipio": "Vall d'Alba", "Web": "www.calparadis.es", "Distinción": "1* MICHELIN" }, "geometry": { "type": "Point", "coordinates": [ -0.033940349906068, 40.17677394070251, 0.0 ] } }
]
}
